<annotation>
	<folder>data</folder>
	<filename>2_1_086.jpg</filename>
	<path>D:\XINjianwenjianjia\buzzzzzzzzzzzzzzzzzzz\labelImg_windows_v1.8.1\windows_v1.8.1\data\2_1_086.jpg</path>
	<source>
		<database>Unknown</database>
	</source>
	<size>
		<width>2448</width>
		<height>2048</height>
		<depth>3</depth>
	</size>
	<segmented>0</segmented>
	<object>
		<name>jiegeng</name>
		<pose>Unspecified</pose>
		<truncated>0</truncated>
		<difficult>0</difficult>
		<bndbox>
			<xmin>1274</xmin>
			<ymin>201</ymin>
			<xmax>1860</xmax>
			<ymax>818</ymax>
		</bndbox>
	</object>
	<object>
		<name>danshen</name>
		<pose>Unspecified</pose>
		<truncated>0</truncated>
		<difficult>0</difficult>
		<bndbox>
			<xmin>1696</xmin>
			<ymin>1069</ymin>
			<xmax>2349</xmax>
			<ymax>1781</ymax>
		</bndbox>
	</object>
	<object>
		<name>baizhi</name>
		<pose>Unspecified</pose>
		<truncated>0</truncated>
		<difficult>0</difficult>
		<bndbox>
			<xmin>254</xmin>
			<ymin>1389</ymin>
			<xmax>843</xmax>
			<ymax>1894</ymax>
		</bndbox>
	</object>
	<object>
		<name>gaoliangjiang</name>
		<pose>Unspecified</pose>
		<truncated>0</truncated>
		<difficult>0</difficult>
		<bndbox>
			<xmin>865</xmin>
			<ymin>841</ymin>
			<xmax>1438</xmax>
			<ymax>1332</ymax>
		</bndbox>
	</object>
	<object>
		<name>yuzhu</name>
		<pose>Unspecified</pose>
		<truncated>0</truncated>
		<difficult>0</difficult>
		<bndbox>
			<xmin>269</xmin>
			<ymin>172</ymin>
			<xmax>718</xmax>
			<ymax>814</ymax>
		</bndbox>
	</object>
</annotation>
